{
  "multipart": [
    {
      "when": {
        "facing": "north"
      },
      "apply": {
        "model": "superposition:block/computer"
      }
    },
    {
      "when": {
        "facing": "south"
      },
      "apply": {
        "model": "superposition:block/computer",
        "y": 180
      }
    },
    {
      "when": {
        "facing": "west"
      },
      "apply": {
        "model": "superposition:block/computer",
        "y": 270
      }
    },
    {
      "when": {
        "facing": "east"
      },
      "apply": {
        "model": "superposition:block/computer",
        "y": 90
      }
    }
  ]
}